LICENSE
MANIFEST.in
setup.cfg
setup.py
ds_lime.egg-info/PKG-INFO
ds_lime.egg-info/SOURCES.txt
ds_lime.egg-info/dependency_links.txt
ds_lime.egg-info/not-zip-safe
ds_lime.egg-info/pbr.json
ds_lime.egg-info/requires.txt
ds_lime.egg-info/top_level.txt
lime/__init__.py
lime/bundle.js
lime/discretize.py
lime/exceptions.py
lime/explanation.py
lime/lime_base.py
lime/lime_image.py
lime/lime_tabular.py
lime/lime_text.py
lime/webpack.config.js